simple_calculator_fath_alrahman_ahmed/__init__.py
simple_calculator_fath_alrahman_ahmed-0.1.0.dist-info/licenses/LICENSE
simple_calculator_fath_alrahman_ahmed-0.1.0.dist-info/METADATA
simple_calculator_fath_alrahman_ahmed-0.1.0.dist-info/WHEEL
simple_calculator_fath_alrahman_ahmed-0.1.0.dist-info/top_level.txt
simple_calculator_fath_alrahman_ahmed-0.1.0.dist-info/RECORD
