Metadata-Version: 2.4
Name: simple-calculator-fath-alrahman-ahmed
Version: 0.1.0
Summary: A simple calculator package for basic math operations.
Home-page: https://github.com/fath-alrahman-ahmed/simple-calculator-fath-alrahman-ahmed
Author: Fath Alrahman Ahmed
Author-email: fath.alrahman.ahmed@example.com
Classifier: Programming Language :: Python :: 3
Classifier: License :: OSI Approved :: MIT License
Classifier: Operating System :: OS Independent
Requires-Python: >=3.6
License-File: LICENSE
Dynamic: author
Dynamic: author-email
Dynamic: classifier
Dynamic: description
Dynamic: description-content-type
Dynamic: home-page
Dynamic: license-file
Dynamic: requires-python
Dynamic: summary
